{
  "productName": "overlayed",
  "appId": "com.hacksore.overlayed",
  "directories": {
    "buildResources": "buildResources",
    "output": "dist"
  },
  "files": [
    "build/**/*",
    "node_modules/**/*"
  ],
  "mac": {
    "target": ["zip"],
    "artifactName": "${productName}-${version}-${os}.${ext}",
    "icon": "build/img/icon-mac.icns",
    "publish" : []
  },
  "win": {
    "target": ["zip"],
    "artifactName": "${productName}-${version}-${os}.${ext}",
    "icon": "build/img/icon.png",
    "publish" : []
  },
  "linux": {
    "target": ["zip"],
    "artifactName": "${productName}-${version}-${os}.${ext}",
    "icon": "build/img/icon.png",
    "publish" : []
  }
}